{
	"name": "df_Functions_Demo_copy1",
	"properties": {
		"type": "MappingDataFlow",
		"typeProperties": {
			"sources": [
				{
					"dataset": {
						"referenceName": "DS_XML",
						"type": "DatasetReference"
					},
					"name": "source"
				}
			],
			"sinks": [],
			"transformations": [],
			"scriptLines": [
				"source(output(",
				"          catalog as (book as ({@id} as string, author as string, datetime as timestamp, description as string, genre as string, price as double, publish_date as date, title as string)[])",
				"     ),",
				"     allowSchemaDrift: true,",
				"     validateSchema: false,",
				"     ignoreNoFilesFound: false,",
				"     validationMode: 'none',",
				"     namespaces: false) ~> source"
			]
		}
	}
}